{
  "_fv": 13,
  "_type": "potion",
  "definition": {
    "name": "Wind Enclosure Effect",
    "effectName": "Wind Enclosure Effect",
    "icon": "blankscrollgui.png",
    "color": {
      "value": -1,
      "falpha": 0.0
    },
    "isInstant": false,
    "isBad": true,
    "isBenefitical": false,
    "registerPotionType": false,
    "renderStatusInInventory": false,
    "renderStatusInHUD": false,
    "onStarted": {
      "name": "Heavywindparticles"
    },
    "onActiveTick": {
      "name": "WindEnclosureEffectOnPotionActiveTick"
    },
    "onExpired": {
      "name": "Heavywindparticles"
    }
  }
}